MANIFEST.in
setup.py
datapkg/__init__.py
datapkg/config.py
datapkg/db.py
datapkg/download.py
datapkg/metadata.py
datapkg/package.py
datapkg/repository.py
datapkg/spec.py
datapkg/upload.py
datapkg/util.py
datapkg.egg-info/PKG-INFO
datapkg.egg-info/SOURCES.txt
datapkg.egg-info/dependency_links.txt
datapkg.egg-info/entry_points.txt
datapkg.egg-info/not-zip-safe
datapkg.egg-info/requires.txt
datapkg.egg-info/top_level.txt
datapkg/cli/__init__.py
datapkg/cli/base.py
datapkg/cli/download.py
datapkg/cli/standard.py
datapkg/cli/upload.py
datapkg/distribution/__init__.py
datapkg/distribution/base.py
datapkg/distribution/jsondist.py
datapkg/index/__init__.py
datapkg/index/base.py
datapkg/index/ckan.py
datapkg/index/db.py
datapkg/tests/__init__.py
datapkg/tests/base.py
datapkg/tests/test_cli.py
datapkg/tests/test_config.py
datapkg/tests/test_distribution.py
datapkg/tests/test_download.py
datapkg/tests/test_metadata.py
datapkg/tests/test_misc.py
datapkg/tests/test_package.py
datapkg/tests/test_repository.py
datapkg/tests/test_setuppy.py
datapkg/tests/test_spec.py
datapkg/tests/test_upload.py
datapkg/tests/test_util.py
datapkg/tests/index/__init__.py
datapkg/tests/index/test_base.py
datapkg/tests/index/test_ckan.py
datapkg/tests/index/test_db.py
doc/CHANGELOG.rst
doc/api.rst
doc/conf.py
doc/design.rst
doc/distribution.rst
doc/extending.rst
doc/external.rst
doc/index.rst
doc/install.rst
doc/license.rst
doc/manual.rst
doc/overview.dia
doc/overview.png
doc/research.rst
doc/spec.rst
doc/usecases.rst
doc/_static/.place-holder
doc/_templates/.place-holder