Metadata-Version: 1.0
Name: datapkg
Version: 0.9
Summary: datapkg (data package): data packaging system and utilities
Home-page: http://okfn.org/projects/datapkg
Author: Open Knowledge Foundation
Author-email: info@okfn.org
License: MIT
Keywords: data,packaging,component,tool
Platform: UNKNOWN
